{"asset_id":"AGIX","quote_currency":"IDR","indicator_summary":{"overall":40,"overall_action":"BUY","buy":2,"sell":2,"neutral":1},"oscillator":{"summary":{"buy":1,"sell":0,"neutral":1},"components":[{"name":"RSI","action":"NEUTRAL","value":54.1346},{"name":"MACD","action":"BUY","value":227.4119}]},"moving_average":{"summary":{"buy":1,"sell":2,"neutral":0},"components":[{"name":"MA-50","action":"BUY","value":13561.6661},{"name":"MA-100","action":"SELL","value":14928.0845},{"name":"MA-200","action":"SELL","value":16190.0879}]}}