{"asset_id":"BTC","quote_currency":"IDR","indicator_summary":{"overall":80,"overall_action":"BUY","buy":4,"sell":1,"neutral":0},"oscillator":{"summary":{"buy":1,"sell":1,"neutral":0},"components":[{"name":"RSI","action":"SELL","value":72.4397},{"name":"MACD","action":"BUY","value":8167431.9488}]},"moving_average":{"summary":{"buy":3,"sell":0,"neutral":0},"components":[{"name":"MA-50","action":"BUY","value":1066622554.0388},{"name":"MA-100","action":"BUY","value":1077758146.4265},{"name":"MA-200","action":"BUY","value":1072173136.3706}]}}