{"asset_id":"ILV","quote_currency":"IDR","indicator_summary":{"overall":80,"overall_action":"SELL","buy":1,"sell":4,"neutral":0},"oscillator":{"summary":{"buy":1,"sell":1,"neutral":0},"components":[{"name":"RSI","action":"BUY","value":30.6544},{"name":"MACD","action":"SELL","value":-22399.2811}]},"moving_average":{"summary":{"buy":0,"sell":3,"neutral":0},"components":[{"name":"MA-50","action":"SELL","value":1551790.0894},{"name":"MA-100","action":"SELL","value":1582958.3985},{"name":"MA-200","action":"SELL","value":1778375.8777}]}}