{"asset_id":"OMNI","quote_currency":"IDR","indicator_summary":{"overall":80,"overall_action":"BUY","buy":4,"sell":1,"neutral":0},"oscillator":{"summary":{"buy":1,"sell":1,"neutral":0},"components":[{"name":"RSI","action":"SELL","value":75.0283},{"name":"MACD","action":"BUY","value":5056.6347}]},"moving_average":{"summary":{"buy":3,"sell":0,"neutral":0},"components":[{"name":"MA-50","action":"BUY","value":330113.3488},{"name":"MA-100","action":"BUY","value":338939.0702},{"name":"MA-200","action":"BUY","value":327800.0951}]}}