{"symbol":"1000SATS","asset_name":"SATS","asset_logo":"https://www.cryptocompare.com/media/44154304/1000sats.png","quote_currency":"IDR","currency_symbol":"Rp","transaction_type":["MARKET","LIMIT"],"market_cap_label":"8,67T","current_supply":0,"maximum_supply":2100000000000,"start_date":1678320000000,"description":"SATS adalah token BRC-20 yang memberi penghormatan kepada satoshi. SATS adalah singkatan dari satoshi, unit terkecil dari Bitcoin. Satu satoshi sama dengan 0,00000001 BTC. Harap dicatat bahwa token tersebut adalah token meme dan ditulis oleh tim anonim. 1000SATS adalah 1000 kali SATS","weiss_rating":{"rating":null,"market_performance_rating":null,"technology_adoption_rating":null},"community":{"official_site":null,"twitch":null,"twitter":null,"telegram":null,"white_paper":null},"price_info":{"high_label":"4,441527","low_label":"4,068478","price":4.134144,"price_label":"4,134144","price_in_idr_label":null,"price_in_idr":null,"price_change":{"24h":{"amount_label":"-0,232463","amount":-0.23246369999999938,"rate_label":"-5,32","rate":-0.053236680730444234,"graph_data":[4.366607699999999,4.3566848,4.375204399999999,4.409580699999999,4.363129600000001,4.351571,4.1676705,4.1867969,4.1803964,4.131344899999999,4.153634,4.1276048,4.1073636,4.1019156,4.098140699999999,4.1156832,4.12776,4.1436021,4.1425769,4.1151879000000005,4.125986999999999,4.134399999999999,4.1330184,4.134144]}}},"halt_config":{"warning_info_text":null,"popup_info_text":null,"is_graph_enabled":true,"is_buy_enabled":true,"is_sell_enabled":true,"is_withdraw_enabled":true,"is_deposit_enabled":true,"is_listed":true},"volume24h_label":"53,52M","coin_labels":["NEW_COIN"],"minimum_amount":16150,"minimum_quantity":1,"maximum_quantity":36348600000,"minimum_tick":1,"quote_tick":1e-7,"decimal_point":{"price":6}}