{"symbol":"ACE","asset_name":"Fusionist","asset_logo":"https://s2.coinmarketcap.com/static/img/coins/200x200/28674.png","quote_currency":"IDR","currency_symbol":"Rp","transaction_type":["MARKET","LIMIT"],"market_cap_label":"0","current_supply":0,"maximum_supply":0,"start_date":1703584800361,"description":"Apa itu Fusionist?\nFusionist adalah sebuah game AAA yang dikembangkan secara mandiri. Klien game ini menggunakan mesin Unity, dengan bagian rendering menggunakan HDRP (High Definition Render Pipeline) untuk mencapai efek visual AAA.\nBagian jaringan mengadopsi teknologi sinkronisasi real-time (protokol KCP + flatbuffer), dan semua hasil perhitungan ditentukan oleh backend untuk memastikan tidak ada kemungkinan kecurangan.\nSelain itu, para pengembang telah mengembangkan klien ringan menggunakan teknologi Unity WebGL, yang dapat berjalan di PC atau perangkat mobile, memastikan maksimalisasi jangkauan pengguna.","weiss_rating":{"rating":null,"market_performance_rating":null,"technology_adoption_rating":null},"community":{"official_site":"https://www.fusionist.io/","twitch":null,"twitter":"https://twitter.com/fusionistio","telegram":"https://t.me/fusionistann","white_paper":null},"price_info":{"high_label":"92.329,03","low_label":"83.647,38","price":89708.581,"price_label":"89.708,58","price_in_idr_label":null,"price_in_idr":null,"price_change":{"24h":{"amount_label":"4.825,42","amount":4825.420000000013,"rate_label":"5,68","rate":0.05684778869156408,"graph_data":[84883.161,84835.014,84107.568,84209.103,85760.148,86861.808,86676.06999999999,87336.323,86762.90000000001,86161.848,85946.952,86032.90999999999,86059.701,86644.9,86795.234,86274.448,88132.339,87487.40000000001,87771.222,89104.276,90430.648,90298.56000000001,88855.43999999999,89708.581]}}},"halt_config":{"warning_info_text":null,"popup_info_text":null,"is_graph_enabled":true,"is_buy_enabled":true,"is_sell_enabled":true,"is_withdraw_enabled":true,"is_deposit_enabled":true,"is_listed":true},"volume24h_label":"197,45M","coin_labels":null,"minimum_amount":16097,"minimum_quantity":0.1,"maximum_quantity":100000,"minimum_tick":0.1,"quote_tick":0.001,"decimal_point":{"price":2}}