{"symbol":"AI","asset_name":"Sleepless","asset_logo":"https://www.cryptocompare.com/media/44221380/ai.png","quote_currency":"IDR","currency_symbol":"Rp","transaction_type":["MARKET","LIMIT"],"market_cap_label":"0","current_supply":null,"maximum_supply":null,"start_date":null,"description":"Sleepless AI adalah platform game Web3+AI yang inovatif, dengan cerdik memadukan kecerdasan buatan dan teknologi blockchain. Pada intinya, Sleepless AI bertujuan untuk merevolusi industri game dengan pendekatan unik dan keahlian luas yang dimiliki timnya.","weiss_rating":{"rating":null,"market_performance_rating":null,"technology_adoption_rating":null},"community":{"official_site":"https://www.sleeplessai.net/home","twitch":null,"twitter":"https://twitter.com/SleeplessAI_Lab","telegram":"https://t.me/SleeplessAIGroup","white_paper":"https://sleepless-ai.gitbook.io/him/"},"price_info":{"high_label":"12.124,77","low_label":"10.865,51","price":11395.607999999998,"price_label":"11.395,6","price_in_idr_label":null,"price_in_idr":null,"price_change":{"24h":{"amount_label":"75,943999","amount":75.9439999999995,"rate_label":"0,67","rate":0.006709033059638476,"graph_data":[11319.663999999999,11243.592,11243.592,10996.353000000001,11161.402,11296.96,11195.712000000001,11093.836000000001,11011.781,11142.390000000001,11225.124000000002,11372.822999999999,11372.13,11355.72,11372.13,11520.521999999999,11618.988,11648.26,11696.765,11648.26,11763.101999999999,11676.042,11427.314999999999,11379.234999999999]}}},"halt_config":{"warning_info_text":null,"popup_info_text":null,"is_graph_enabled":true,"is_buy_enabled":true,"is_sell_enabled":true,"is_withdraw_enabled":true,"is_deposit_enabled":true,"is_listed":true},"volume24h_label":"103,29M","coin_labels":null,"minimum_amount":81865,"minimum_quantity":0.1,"maximum_quantity":92141578,"minimum_tick":0.1,"quote_tick":0.001,"decimal_point":{"price":2}}