{"symbol":"ALT","asset_name":"Altlayer","asset_logo":"https://s2.coinmarketcap.com/static/img/coins/200x200/29073.png","quote_currency":"IDR","currency_symbol":"Rp","transaction_type":["MARKET","LIMIT"],"market_cap_label":"47,64T","current_supply":0,"maximum_supply":0,"start_date":1706851989361,"description":"AltLayer adalah protokol terdesentralisasi yang memfasilitasi peluncuran native dan restaked rollup dengan optimistic dan zk rollup stacks.","weiss_rating":{"rating":null,"market_performance_rating":null,"technology_adoption_rating":null},"community":{"official_site":"https://altlayer.io/","twitch":null,"twitter":"https://twitter.com/alt_layer","telegram":"https://t.me/altlayer","white_paper":"https://docs.altlayer.io/"},"price_info":{"high_label":"5.196,0549","low_label":"4.650,6164","price":4768.61145,"price_label":"4.768,6114","price_in_idr_label":null,"price_in_idr":null,"price_change":{"24h":{"amount_label":"-371,2341","amount":-371.2341699999997,"rate_label":"-7,22","rate":-0.0722267160234279,"graph_data":[5139.84562,5053.30228,5052.5053800000005,5049.63459,5027.32334,5005.31352,4954.98825,5011.86776,4979.19691,5010.327359999999,5042.65833,5057.922140000001,4985.20098,5000.81938,4947.19257,4949.33166,4835.2880700000005,4837.4722,4669.353,4736.3921,4727.865,4742.90999,4769.90322,4765.5876]}}},"halt_config":{"warning_info_text":null,"popup_info_text":null,"is_graph_enabled":true,"is_buy_enabled":true,"is_sell_enabled":true,"is_withdraw_enabled":true,"is_deposit_enabled":true,"is_listed":true},"volume24h_label":"457,78M","coin_labels":null,"minimum_amount":79575,"minimum_quantity":1,"maximum_quantity":92141578,"minimum_tick":1,"quote_tick":0.00001,"decimal_point":{"price":4}}