{"symbol":"AXS","asset_name":"Axie Infinity Shards","asset_logo":"https://www.cryptocompare.com/media/43687841/axs.png","quote_currency":"IDR","currency_symbol":"Rp","transaction_type":["MARKET","LIMIT"],"market_cap_label":"30,56T","current_supply":147314369,"maximum_supply":null,"start_date":1619395200000,"description":"Axie Infinity Shards (AXS) adalah governance token dari game populer berbasis blockchain Axie Infinity. Game ini dibuat oleh SkyMavis dan memungkinkan pemain memperoleh penghasilan melalui token non-fungible (NFT), dengan membiakkan, mempertarungkan, dan memperdagangkan hewan peliharaan digital yang disebut Axies.\r\n\r\nPemain membutuhkan token AXS untuk memperdagangkan Axies dan dapat staking koin mereka untuk mendapatkan hadiah mingguan, serta berpartisipasi dalam tata kelola protokol. Pemain baru harus membeli setidaknya tiga token, dengan harga ether, untuk benar-benar berpartisipasi dalam permainan.\r\n\r\nSetiap Axie adalah NFT sendiri dengan atribut yang berbeda. Hewan peliharaan ini dapat memasuki pertempuran untuk mendapatkan exp poin dan hal lainnya. Axie juga dapat dibiakkan untuk membuat NFT Axie baru dengan atribut berbeda, yang kemudian dapat digunakan utk bertarung atau dijual di pasar Axie.\r\n\r\nMenurut DappRadar, game Axie Infinity memiliki banyak cara untuk mendapatkan pendapatan dan telah mendapatkan popularitas di negara-negara berkembang seperti Brasil, India, Indonesia, dan Venezuela. Pemain yang berdedikasi dilaporkan dapat memperoleh lebih dari $1.000 sebulan dalam permainan.\r\n\r\nGame Axie Infinity dibuat kembali pada tahun 2018 oleh Sky Mavis, sebuah perusahaan yang didirikan oleh Trung Nguyen dan Aleksander Larsen. Secara total, tim Axie Infinity sekarang memiliki 25 karyawan full-time yang secara aktif bekerja untuk meningkatkan permainan.","weiss_rating":{"rating":"C+","market_performance_rating":"C-","technology_adoption_rating":"B-"},"community":{"official_site":"https://axieinfinity.com/axs","twitch":"","twitter":"https://twitter.com/AxieInfinity","telegram":"https://t.me/axieinfinity","white_paper":"https://whitepaper.axieinfinity.com/"},"price_info":{"high_label":"116.232,89","low_label":"108.216,42","price":115870.797,"price_label":"115.870,79","price_in_idr_label":null,"price_in_idr":null,"price_change":{"24h":{"amount_label":"2.838,8646","amount":2838.864600000001,"rate_label":"2,51","rate":0.02511559821833145,"graph_data":[113031.9324,113758.03300000001,115266.3745,115459.98449999999,114905.18759999999,114678.831,114123.169,113534.821,113723.97799999999,114861.68,113720.85299999999,113826.3135,113801.92000000001,113724.26999999999,113983.576,112731.03,111408.624,111401.8,112511.90000000001,111483.425,109336.872,109784.402,113014.88,116090.56]}}},"halt_config":{"warning_info_text":null,"popup_info_text":null,"is_graph_enabled":true,"is_buy_enabled":true,"is_sell_enabled":true,"is_withdraw_enabled":true,"is_deposit_enabled":true,"is_listed":true},"volume24h_label":"435,57M","coin_labels":null,"minimum_amount":16359,"minimum_quantity":0.01,"maximum_quantity":57036,"minimum_tick":0.01,"quote_tick":0.0001,"decimal_point":{"price":2}}