{"symbol":"ETHFI","asset_name":"ether.fi","asset_logo":"https://s2.coinmarketcap.com/static/img/coins/200x200/29814.png","quote_currency":"IDR","currency_symbol":"Rp","transaction_type":["MARKET","LIMIT"],"market_cap_label":"41,79T","current_supply":0,"maximum_supply":0,"start_date":1711553589361,"description":null,"weiss_rating":{"rating":null,"market_performance_rating":null,"technology_adoption_rating":null},"community":{"official_site":"https://www.ether.fi/","twitch":null,"twitter":"https://twitter.com/ether_fi","telegram":"https://t.me/+C3fpSjmPqzA5NTVh","white_paper":"https://etherfi.gitbook.io/etherfi/ether.fi-whitepaper"},"price_info":{"high_label":"46.347,17","low_label":"41.028,67","price":41789.475000000006,"price_label":"41.789,47","price_in_idr_label":null,"price_in_idr":null,"price_change":{"24h":{"amount_label":"-4.382,0579","amount":-4382.057999999997,"rate_label":"-9,49","rate":-0.09490821974656975,"graph_data":[46171.533,45374.513999999996,45394.005000000005,45380.36,45608.199,45141.546,44869.85,45119.58,44724.372,44886.316,44974.02,44707.32,44597.335,44487.9,44605.945999999996,44287.488000000005,44985.032,44352.366,44391.412000000004,43412.284,41941.6,41756.505,41819.907999999996,41789.475000000006]}}},"halt_config":{"warning_info_text":null,"popup_info_text":null,"is_graph_enabled":true,"is_buy_enabled":true,"is_sell_enabled":true,"is_withdraw_enabled":true,"is_deposit_enabled":true,"is_listed":true},"volume24h_label":"413,65M","coin_labels":null,"minimum_amount":82425,"minimum_quantity":0.1,"maximum_quantity":92141578,"minimum_tick":0.1,"quote_tick":0.001,"decimal_point":{"price":2}}