{"symbol":"GLMR","asset_name":"Moonbeam","asset_logo":"https://www.cryptocompare.com/media/39500747/glmr.png","quote_currency":"IDR","currency_symbol":"Rp","transaction_type":["MARKET","LIMIT"],"market_cap_label":"3,68T","current_supply":883058601,"maximum_supply":null,"start_date":1629331200000,"description":"Moonbeam adalah parachain kontrak pintar yang kompatibel dengan Ethereum di Polkadot. Moonbeam memudahkan penggunaan alat pengembang Ethereum yang populer untuk membangun atau menyebarkan ulang proyek Solidity dalam lingkungan berbasis Substrat.\r\n\r\nMoonbeam lebih dari sekadar implementasi EVM: Moonbeam adalah parachain yang sangat terspesialisasi yang mencerminkan RPC Web3 Ethereum, akun, kunci, langganan, log, dan banyak lagi. Platform Moonbeam memperluas rangkaian fitur dasar Ethereum dengan fitur tambahan seperti tata kelola on-chain, staking, dan integrasi lintas-rantai.\r\n\r\nKompatibilitas Ethereum Moonbeam tidak tertandingi:\r\n\r\nPerubahan Minimal: pengembang dapat langsung menggunakan kontrak pintar Solidity yang sudah ada, tanpa perlu menulis ulang atau mengkonfigurasi ulang\r\n\r\nGunakan Alat Pengembang yang Ada: hubungkan alat populer seperti MetaMask, Hardhat, Waffle, Remix, dan Truffle melalui satu set lengkap titik akhir RPC Web3. Gunakan pustaka Javascript yang terkenal seperti Web3.Js atau Ethers.Js.\r\n\r\nAkun, Alamat, dan Tanda Tangan Terpadu: gunakan akun Ethereum H160 & tanda tangan ECDSA Anda yang sudah ada untuk berinteraksi dengan Moonbeam\r\n\r\nManfaatkan Integrasi Terbanyak di Polkadot: gunakan oracle, jembatan, dompet, dan alat lain yang sudah ada di Moonbeam\r\n\r\nMoonbeam menyediakan integrasi dan konektivitas antara Polkadot Parachains serta dengan rantai lain seperti Ethereum dan Bitcoin melalui jembatan. Moonbeam dimulai pada tahun 2019 oleh Derek Yoo dari Pure Stake.","weiss_rating":{"rating":null,"market_performance_rating":null,"technology_adoption_rating":null},"community":{"official_site":"https://moonbeam.network/","twitch":null,"twitter":"https://twitter.com/moonbeamnetwork","telegram":"https://t.me/Moonbeam_Official","white_paper":"https://docs.moonbeam.network/"},"price_info":{"high_label":"3.352,3334","low_label":"2.996,8197","price":3279.2736999999997,"price_label":"3.279,2736","price_in_idr_label":null,"price_in_idr":null,"price_change":{"24h":{"amount_label":"143,6664","amount":143.66649999999981,"rate_label":"4,58","rate":0.04581776059195164,"graph_data":[3135.6072,3179.9729,3194.9428,3180.554,3213.1983,3191.6591999999996,3172.1508000000003,3134.578,3114.8740000000003,3060.816,3051.3626000000004,3113.2955,3079.5443999999998,3121.9888,3093.1704,3081.5353999999998,3071.6122,3254.208,3260.736,3214.8032,3270.7637999999997,3282.0166,3272.7522,3278.6296]}}},"halt_config":{"warning_info_text":null,"popup_info_text":null,"is_graph_enabled":true,"is_buy_enabled":true,"is_sell_enabled":true,"is_withdraw_enabled":true,"is_deposit_enabled":true,"is_listed":true},"volume24h_label":"123,93M","coin_labels":null,"minimum_amount":82130,"minimum_quantity":0.1,"maximum_quantity":92141578,"minimum_tick":0.1,"quote_tick":0.0001,"decimal_point":{"price":4}}