{"symbol":"JUP","asset_name":"Jupiter","asset_logo":"https://www.cryptocompare.com/media/44222180/jup.png","quote_currency":"IDR","currency_symbol":"Rp","transaction_type":["MARKET","LIMIT"],"market_cap_label":"0","current_supply":0,"maximum_supply":0,"start_date":null,"description":"Sebagai salah satu mesin agregasi swap tercanggih di industri, Jupiter unggul dalam menyediakan infrastruktur likuiditas penting untuk ekosistem Solana. Selain itu, Jupiter secara aktif memperluas penawaran produk DeFi-nya, menampilkan rangkaian komprehensif yang mencakup Limit Order, DCA/TWAP, Bridge Comparator, dan Perpetuals Trading.","weiss_rating":{"rating":null,"market_performance_rating":null,"technology_adoption_rating":null},"community":{"official_site":"https://jup.ag/","twitch":null,"twitter":"https://twitter.com/JupiterExchange","telegram":null,"white_paper":null},"price_info":{"high_label":"22.462,57","low_label":"20.758,36","price":21192.9078,"price_label":"21.192,9","price_in_idr_label":null,"price_in_idr":null,"price_change":{"24h":{"amount_label":"-714,6959","amount":-714.6959999999999,"rate_label":"-3,26","rate":-0.032623193596371315,"graph_data":[21907.6038,21953.477000000003,22068.287999999997,21829.321799999998,21279.772,21111.094800000003,21257.298300000002,21565.4214,21977.0182,21982.643200000002,21808.639499999997,21884.2578,21717.1912,21581.7846,21415.586,21577.7124,21558.991,21007.440000000002,21251.8762,21367.9186,21287.0426,21316.055,21432.9752,21191.294700000002]}}},"halt_config":{"warning_info_text":null,"popup_info_text":null,"is_graph_enabled":true,"is_buy_enabled":true,"is_sell_enabled":true,"is_withdraw_enabled":true,"is_deposit_enabled":true,"is_listed":true},"volume24h_label":"462,57M","coin_labels":null,"minimum_amount":16129,"minimum_quantity":1,"maximum_quantity":200000,"minimum_tick":0.001,"quote_tick":0.0001,"decimal_point":{"price":2}}