{"symbol":"MANTA","asset_name":"Manta Network","asset_logo":"https://www.cryptocompare.com/media/44213520/manta.png","quote_currency":"IDR","currency_symbol":"Rp","transaction_type":["MARKET","LIMIT"],"market_cap_label":"0","current_supply":0,"maximum_supply":0,"start_date":null,"description":"Manta Network berfungsi sebagai gerbang untuk aplikasi ZK, dengan menggunakan blockchain modular dan zkEVM untuk menetapkan paradigma baru untuk platform smart contract L2.\r\nManta Pacific mengatasi kekhawatiran tentang kegunaan melalui desain infrastruktur modular, memungkinkan integrasi yang mulus dari DA modular dan zkEVM untuk terus meningkatkan pengalaman pengguna dari waktu ke waktu.","weiss_rating":{"rating":null,"market_performance_rating":null,"technology_adoption_rating":null},"community":{"official_site":null,"twitch":null,"twitter":null,"telegram":null,"white_paper":null},"price_info":{"high_label":"28.349,5","low_label":"26.325,06","price":27630.18,"price_label":"27.630,18","price_in_idr_label":null,"price_in_idr":null,"price_change":{"24h":{"amount_label":"1.158,93","amount":1158.9300000000003,"rate_label":"4,37","rate":0.04378070548236295,"graph_data":[26471.25,26521.453999999998,26855.998,26727.516,26617.02,27072.849000000002,27401.66,27475.2,27636.33,27682.814,27979.29,27757.726,27841.957000000002,27791.76,27414.695,27480.993000000002,28044.853000000003,27858.816,28023.021,27864.543999999998,28028.232,27596.719,27527.292,27662.496]}}},"halt_config":{"warning_info_text":null,"popup_info_text":null,"is_graph_enabled":true,"is_buy_enabled":true,"is_sell_enabled":true,"is_withdraw_enabled":true,"is_deposit_enabled":true,"is_listed":true},"volume24h_label":"184,86M","coin_labels":null,"minimum_amount":80790,"minimum_quantity":0.1,"maximum_quantity":92141578,"minimum_tick":0.1,"quote_tick":0.001,"decimal_point":{"price":2}}