{"symbol":"OMNI","asset_name":"Omni Network","asset_logo":"https://s2.coinmarketcap.com/static/img/coins/200x200/30315.png","quote_currency":"IDR","currency_symbol":"Rp","transaction_type":["MARKET","LIMIT"],"market_cap_label":"70,46M","current_supply":0,"maximum_supply":0,"start_date":1713432789361,"description":null,"weiss_rating":{"rating":null,"market_performance_rating":null,"technology_adoption_rating":null},"community":{"official_site":"https://omni.network/","twitch":null,"twitter":"https://twitter.com/OmniFDN","telegram":"https://t.me/OmniFDN","white_paper":"https://docs.omni.network/whitepaper.pdf"},"price_info":{"high_label":"210.762,5","low_label":"193.461,6","price":194146.68000000002,"price_label":"194.146,68","price_in_idr_label":null,"price_in_idr":null,"price_change":{"24h":{"amount_label":"-10.744,37","amount":-10744.379999999976,"rate_label":"-5,24","rate":-0.05243947686150863,"graph_data":[204891.06,205393.80000000002,205858.8,207013.68,204414.03999999998,202680.12,202669.56,203224.79,203637.06,203961.84,201950.21,203399.91999999998,203524.78999999998,206011.96,207223.58,202512.5,201241.26,197676.59999999998,198110.64,198832.68,199220.9,196237.8,196099.8,194146.68000000002]}}},"halt_config":{"warning_info_text":null,"popup_info_text":null,"is_graph_enabled":true,"is_buy_enabled":true,"is_sell_enabled":true,"is_withdraw_enabled":true,"is_deposit_enabled":true,"is_listed":true},"volume24h_label":"0","coin_labels":null,"minimum_amount":81165,"minimum_quantity":0.01,"maximum_quantity":9222449,"minimum_tick":0.01,"quote_tick":0.01,"decimal_point":{"price":2}}