{"symbol":"ONDO","asset_name":"Ondo","asset_logo":"https://www.cryptocompare.com/media/44221391/ondo.png","quote_currency":"IDR","currency_symbol":"Rp","transaction_type":["MARKET","LIMIT"],"market_cap_label":"117,84T","current_supply":1990929088,"maximum_supply":null,"start_date":1651104000000,"description":"Pemegang token ONDO bisa bantu menjalankan protokol Ondo DAO dan Flux Finance, di dalam parameter ekonomi dan peningkatan kontrak pintar, melalui proposal tata kelola on-chain.","weiss_rating":{"rating":null,"market_performance_rating":null,"technology_adoption_rating":null},"community":{"official_site":"https://ondo.finance/","twitch":null,"twitter":"https://twitter.com/OndoFinance","telegram":"https://t.me/ondofinance","white_paper":"https://docs.ondo.finance/"},"price_info":{"high_label":"13.017,75","low_label":"11.411,31","price":11732.923499999999,"price_label":"11.732,92","price_in_idr_label":null,"price_in_idr":null,"price_change":{"24h":{"amount_label":"-740,562","amount":-740.5620000000017,"rate_label":"-5,93","rate":-0.05937089516799468,"graph_data":[12473.4855,12420.7545,12850.52165,12731.2815,12914.1798,12707.3526,12784.61283,12718.5804,12558.441,12507.016,12620.478690000002,12526.983180000001,12151.88244,12017.19588,12073.536,11881.88419,11823.012,11582.61254,11775.1065,11612.423999999999,11585.22838,11710.62521,11740.4445,11727.691499999999]}}},"halt_config":{"warning_info_text":{"title":"Pengumuman Unusual Market Activity atas ONDO\n","message":"Transaksi dalam pengawasan khusus dan transaksi beli telah diberhentikan untuk sementara"},"popup_info_text":null,"is_graph_enabled":true,"is_buy_enabled":false,"is_sell_enabled":true,"is_withdraw_enabled":true,"is_deposit_enabled":true,"is_listed":true},"volume24h_label":"1,65T","coin_labels":null,"minimum_amount":16338,"minimum_quantity":1,"maximum_quantity":100000,"minimum_tick":0.01,"quote_tick":0.00001,"decimal_point":{"price":2}}