{"symbol":"ONDO","asset_name":"Ondo","asset_logo":"https://www.cryptocompare.com/media/44221391/ondo.png","quote_currency":"IDR","currency_symbol":"Rp","transaction_type":["MARKET","LIMIT"],"market_cap_label":"203,53T","current_supply":1996530129,"maximum_supply":null,"start_date":1651104000000,"description":"Pemegang token ONDO bisa bantu menjalankan protokol Ondo DAO dan Flux Finance, di dalam parameter ekonomi dan peningkatan kontrak pintar, melalui proposal tata kelola on-chain.","weiss_rating":{"rating":null,"market_performance_rating":null,"technology_adoption_rating":null},"community":{"official_site":"https://ondo.finance/","twitch":null,"twitter":"https://twitter.com/OndoFinance","telegram":"https://t.me/ondofinance","white_paper":"https://docs.ondo.finance/"},"price_info":{"high_label":"21.328,34","low_label":"18.895,22","price":20586.6963,"price_label":"20.586,69","price_in_idr_label":null,"price_in_idr":null,"price_change":{"24h":{"amount_label":"1.540,4533","amount":1540.453300000001,"rate_label":"8,08","rate":0.08087964119747927,"graph_data":[19046.243,19224.6078,19139.4258,19080.819199999998,19374.787500000002,19466.7772,19647.786330000003,19938.3975,20651.71206,20834.1264,20756.2575,21038.724000000002,21163.126,21135.091,21003.3263,20761.7412,20779.314,20728.3532,20485.143900000003,20449.305,20348.414999999997,20707.599000000002,20385.72939,20569.0446]}}},"halt_config":{"warning_info_text":{"title":"Pengumuman Unusual Market Activity atas ONDO\n","message":"Transaksi dalam pengawasan khusus dan transaksi beli telah diberhentikan untuk sementara"},"popup_info_text":null,"is_graph_enabled":true,"is_buy_enabled":false,"is_sell_enabled":true,"is_withdraw_enabled":true,"is_deposit_enabled":true,"is_listed":true},"volume24h_label":"3,35T","coin_labels":null,"minimum_amount":16039,"minimum_quantity":1,"maximum_quantity":100000,"minimum_tick":0.01,"quote_tick":0.00001,"decimal_point":{"price":2}}