{"symbol":"ONDO","asset_name":"Ondo","asset_logo":"https://www.cryptocompare.com/media/44221391/ondo.png","quote_currency":"IDR","currency_symbol":"Rp","transaction_type":["MARKET","LIMIT"],"market_cap_label":"130,57T","current_supply":1989305231,"maximum_supply":null,"start_date":1651104000000,"description":"Pemegang token ONDO bisa bantu menjalankan protokol Ondo DAO dan Flux Finance, di dalam parameter ekonomi dan peningkatan kontrak pintar, melalui proposal tata kelola on-chain.","weiss_rating":{"rating":null,"market_performance_rating":null,"technology_adoption_rating":null},"community":{"official_site":"https://ondo.finance/","twitch":null,"twitter":"https://twitter.com/OndoFinance","telegram":"https://t.me/ondofinance","white_paper":"https://docs.ondo.finance/"},"price_info":{"high_label":"13.111,33","low_label":"12.211,7","price":13087.119059999999,"price_label":"13.087,11","price_in_idr_label":null,"price_in_idr":null,"price_change":{"24h":{"amount_label":"670,9808","amount":670.9808599999997,"rate_label":"5,4","rate":0.054041027024006524,"graph_data":[12416.1382,12545.5653,12489.223,12555.14788,12549.08907,12551.9047,12608.09145,12568.30048,12387.402989999999,12395.55249,12382.731459999999,12540.242,12484.91992,12376.48266,12407.886,12789.885600000001,12751.327000000001,12765.897439999999,12736.652250000001,12768.329880000001,12832.474199999999,12931.08042,13059.899730000001,13078.982020000001]}}},"halt_config":{"warning_info_text":{"title":"Jadwal Pemeliharaan Transaksi Aset Kripto","message":"Transaksi jual dan beli aset kripto sedang melakukan pemeliharaan sistem. Transaksi jual dan beli aset kripto tidak dapat diakses dari pukul 08:00 - 11:30."},"popup_info_text":null,"is_graph_enabled":false,"is_buy_enabled":false,"is_sell_enabled":false,"is_withdraw_enabled":true,"is_deposit_enabled":true,"is_listed":true},"volume24h_label":"0","coin_labels":null,"minimum_amount":16299,"minimum_quantity":1,"maximum_quantity":100000,"minimum_tick":0.01,"quote_tick":0.00001,"decimal_point":{"price":2}}