{"symbol":"PENDLE","asset_name":"Pendle","asset_logo":"https://www.cryptocompare.com/media/37747410/pendle.png","quote_currency":"IDR","currency_symbol":"Rp","transaction_type":["MARKET","LIMIT"],"market_cap_label":"25,03T","current_supply":153893416,"maximum_supply":null,"start_date":1619481600000,"description":"Apa itu Pendle?\r\nPendle adalah protokol yang memungkinkan trading future yield atau token yield-generating melalui sistem AMM miliknya. Dengan membagi underlying berupa yield generating token menjadi Ownership Token (OT) dan future Yield Token (YT). YT adalah representasi yield dari aset underlying dan dapat dijual untuk meraih pendapatan masa depan seecepatnya, atau dibeli untuk melakukan exposure ke ure yield dari aset underlying ini sendiri. Baik YT atau OT bisa digunakan untuk menyediakan likuiditas bagi Pendle untuk mendapatkan extra yield. \r\n\r\nSejarah Pendle\r\nDiluncurkan pada Juni 2021, Pendle adalah protokol yield-aggregating, yang memberi insentif bagi pengumpulan token yield-generating dan pembuatan yield markets pada berbagai platform DeFi. Pendle memungkinkan para pemegang token ini untuk menjadikan token mereka YT atau OT. Para pemilik yield-generating token ini bisa menjual hak yield mereka, memungkinkan mereka untuk mengunci profit mereka dan menerima dana tunai dari depan. Para pembeli hak ini mendapatkan exposure dari pergerakan harga pasar di dalam bentuk yang lebih capital-efficient, sehingga mereka tidak perlu membeli atau melakukan stake pada aset underlying. Sehingga, tidak ada yang perlu dikhawatirkan terkait collateralization atau risiko likuidasi. ","weiss_rating":{"rating":null,"market_performance_rating":null,"technology_adoption_rating":null},"community":{"official_site":"https://www.pendle.finance/","twitch":"","twitter":"https://twitter.com/pendle_fi","telegram":"https://t.me/pendlefinance","white_paper":""},"price_info":{"high_label":"102.622,3","low_label":"93.555,48","price":96971.79400000001,"price_label":"96.971,79","price_in_idr_label":null,"price_in_idr":null,"price_change":{"24h":{"amount_label":"-4.562,0409","amount":-4562.040999999997,"rate_label":"-4,49","rate":-0.04493123893133749,"graph_data":[101533.835,100052.208,98686.632,99633.792,97515.978,95072.765,95520.022,95217.606,95897.181,93908.345,95287.699,96667.053,96747.248,95913.22,95971.39199999999,96153.80500000001,96083.658,95951.52,97078.014,96388.37999999999,96478.592,98110.563,96883.215,96971.79400000001]}}},"halt_config":{"warning_info_text":null,"popup_info_text":null,"is_graph_enabled":true,"is_buy_enabled":true,"is_sell_enabled":true,"is_withdraw_enabled":true,"is_deposit_enabled":true,"is_listed":true},"volume24h_label":"102,57M","coin_labels":null,"minimum_amount":80195,"minimum_quantity":0.1,"maximum_quantity":92141578,"minimum_tick":0.1,"quote_tick":0.001,"decimal_point":{"price":2}}