{"symbol":"PHA","asset_name":"Phala Network","asset_logo":"https://www.cryptocompare.com/media/37305519/pha.png","quote_currency":"IDR","currency_symbol":"Rp","transaction_type":["MARKET","LIMIT"],"market_cap_label":"2,26T","current_supply":639169756,"maximum_supply":null,"start_date":1588204800000,"description":"Phala Network adalah Lapisan Eksekusi (Execution Layer) untuk Web3 AI. Dengan memungkinkan AI untuk memahami dan berinteraksi dengan blockchain, ini membuka penghalang bagi satu miliar pengguna pertama untuk bergabung dengan Web3.\r\n\r\nSistem multi-bukti (multi-proof system) Phala Network adalah jawaban untuk masalah eksekusi AI. Di atas Phala Network, Anda dapat dengan mudah membangun Agen AI yang anti-rusak dan tak terhentikan yang terintegrasi erat dengan kontrak pintar on-chain oleh AI-Agent Contract\r\n\r\nMengagenkan kontrak pintar: Buat Agen AI untuk kontrak pintar menggunakan bahasa alami dan bahasa pemrograman.\r\nTerhubung ke internet multi-agen: Jadikan agen Anda dapat diakses oleh Agen AI lintas rantai lainnya.\r\nLuncurkan Agen AI dan dapatkan insentif: Miliki agen Anda dan bangun ekonomi token yang menguntungkan.","weiss_rating":{"rating":null,"market_performance_rating":null,"technology_adoption_rating":null},"community":{"official_site":"https://phala.network/","twitch":null,"twitter":"https://twitter.com/PhalaNetwork","telegram":"https://t.me/phalanetwork","white_paper":"https://docs.phala.network/introduction/readme"},"price_info":{"high_label":"2.517,9572","low_label":"2.134,5119","price":2254.1954,"price_label":"2.254,1954","price_in_idr_label":null,"price_in_idr":null,"price_change":{"24h":{"amount_label":"-178,6415","amount":-178.64159999999993,"rate_label":"-7,34","rate":-0.07342933373670325,"graph_data":[2432.837,2434.4874999999997,2426.2349999999997,2417.9428000000003,2392.8004,2448.7916,2414.2088000000003,2462.1155,2480.2314,2513.0168000000003,2495.0535,2463.7624,2478.4339999999997,2472.2846999999997,2442.3527,2412.7084999999997,2221.8055,2243.0778,2228.1204000000002,2239.376,2214.8115000000003,2254.1954,2269.1526,2254.1954]}}},"halt_config":{"warning_info_text":null,"popup_info_text":null,"is_graph_enabled":true,"is_buy_enabled":true,"is_sell_enabled":true,"is_withdraw_enabled":true,"is_deposit_enabled":true,"is_listed":true},"volume24h_label":"65,45M","coin_labels":["NEW_COIN"],"minimum_amount":82330,"minimum_quantity":1,"maximum_quantity":92141578,"minimum_tick":1,"quote_tick":0.0001,"decimal_point":{"price":4}}