{"symbol":"PIXEL","asset_name":"Pixels","asset_logo":"https://s2.coinmarketcap.com/static/img/coins/200x200/29335.png","quote_currency":"IDR","currency_symbol":"Rp","transaction_type":["MARKET","LIMIT"],"market_cap_label":"28,76T","current_supply":0,"maximum_supply":0,"start_date":1708666389361,"description":"Pixels (PIXEL) adalah game web3 yang didukung oleh Ronin Network, Ini melibatkan game dunia terbuka yang berkisar seputar pertanian, eksplorasi, dan kreasi. \r\nPIXEL adalah token utilitas dan tata kelola asli di ekosistem Pixels, dan digunakan dalam fungsi berikut: \r\n\r\n- Mata uang dalam game \r\n- Pencetakan NFT: Semua pencetakan NFT masa depan dari Pixels akan berada dalam $PIXEL. \r\n- Keanggotaan VIP: Pengguna akan dapat membeli VIP Battle Pass dalam $PIXEL. \r\n- Persekutuan: Pengguna akan dapat bergabung dengan fitur sosial baru (Persekutuan) dengan menggunakan $PIXEL. \r\n- Peningkatan Kualitas Hidup: Fitur premium dalam game akan dijual dengan harga $PIXEL. \r\n- Tata Kelola: $PIXEL pada akhirnya akan digunakan untuk mengatur perbendaharaan komunitas.","weiss_rating":{"rating":null,"market_performance_rating":null,"technology_adoption_rating":null},"community":{"official_site":"https://www.pixels.xyz/","twitch":null,"twitter":"https://twitter.com/pixels_online","telegram":null,"white_paper":"https://whitepaper.pixels.xyz/"},"price_info":{"high_label":"5.811,7239","low_label":"5.484,044","price":5802.16,"price_label":"5.802,16","price_in_idr_label":null,"price_in_idr":null,"price_change":{"24h":{"amount_label":"250,5434","amount":250.54340000000047,"rate_label":"4,51","rate":0.04512980957654758,"graph_data":[5551.616599999999,5601.375999999999,5608.0936,5595.528499999999,5564.8938,5608.415999999999,5557.363,5572.8918,5570.876,5532.2848,5568.0792,5564.6184,5538.668000000001,5536.523999999999,5559.872,5684.1808,5638.3343,5697.6072,5712.498,5613.1320000000005,5720.7807999999995,5645.7594,5777.8875,5803.389899999999]}}},"halt_config":{"warning_info_text":null,"popup_info_text":null,"is_graph_enabled":true,"is_buy_enabled":true,"is_sell_enabled":true,"is_withdraw_enabled":true,"is_deposit_enabled":true,"is_listed":true},"volume24h_label":"268,92M","coin_labels":null,"minimum_amount":15940,"minimum_quantity":1,"maximum_quantity":200000,"minimum_tick":0.1,"quote_tick":0.0001,"decimal_point":{"price":4}}