{"symbol":"RPL","asset_name":"RocketPool","asset_logo":"https://www.cryptocompare.com/media/43961461/rpl.png","quote_currency":"IDR","currency_symbol":"Rp","transaction_type":["MARKET","LIMIT"],"market_cap_label":"6,3T","current_supply":20369079,"maximum_supply":null,"start_date":1632960000000,"description":"Apa itu Rocket Pool (RPL)?\r\n\r\nRocket Pool adalah protokol Liquid Staking Derivatives (LSD) yang dibuat untuk memenuhi dua kebutuhan, yaitu pengguna atau Stakers yang ingin mendapatkan keuntungan pasif dari staking ETH dan pengguna yang ingin berperan sebagai Smart Node Operator (SNO) atau validator.\r\n\r\nPerbedaannya dengan protokol staking tradisional, dengan Rocket Pool pengguna akan mendapatkan Rocket Pool ETH (rETH) yang nilainya setara dengan ETH yang dimasukkan. Token rETH dapat digunakan pada berbagai platform decentralized finance (DeFi) untuk memaksimalkan keuntungan.\r\n\r\nPengguna dapat bergabung dengan Rocket Pool dengan jaringan operator node terdesentralisasi atau menjalankan node mereka sendiri hanya dengan 16 ETH. Karena nilai tersebut, Rocket Pool menjadi protokol liquid staking terdesentralisasi dengan jumlah validator terbanyak, yakni 2.109 node operator per Februari 2023.","weiss_rating":{"rating":null,"market_performance_rating":null,"technology_adoption_rating":null},"community":{"official_site":"https://rocketpool.net/","twitch":"","twitter":"https://twitter.com/Rocket_Pool","telegram":"","white_paper":"https://docs.rocketpool.net/"},"price_info":{"high_label":"317.983,05","low_label":"303.338,2","price":310651.11,"price_label":"310.651,11","price_in_idr_label":null,"price_in_idr":null,"price_change":{"24h":{"amount_label":"-2.200,24","amount":-2200.240000000049,"rate_label":"-0,7","rate":-0.007032860813929838,"graph_data":[312851.35000000003,309916.3,308665.26,308456.12,307295.4,306910.8,306526.2,308742.77999999997,306517.75,307810.92,307270.41,308826,312376.34,312057.10000000003,313061.60000000003,315295.2,311951.16,311154.95999999996,309881.04000000004,309042,309395.4,309360.60000000003,309477.12000000005,310651.11]}}},"halt_config":{"warning_info_text":null,"popup_info_text":null,"is_graph_enabled":true,"is_buy_enabled":true,"is_sell_enabled":true,"is_withdraw_enabled":true,"is_deposit_enabled":true,"is_listed":true},"volume24h_label":"154,43M","coin_labels":null,"minimum_amount":79700,"minimum_quantity":0.01,"maximum_quantity":9222449,"minimum_tick":0.01,"quote_tick":0.01,"decimal_point":{"price":2}}