{"symbol":"STRK","asset_name":"Starknet","asset_logo":"https://s2.coinmarketcap.com/static/img/coins/200x200/22691.png","quote_currency":"IDR","currency_symbol":"Rp","transaction_type":["MARKET","LIMIT"],"market_cap_label":"185,94T","current_supply":0,"maximum_supply":0,"start_date":1708666389361,"description":"StarkNet adalah Validity-Rollup terdesentralisasi tanpa izin (juga dikenal sebagai “ZK-Rollup”). Ini beroperasi sebagai jaringan L2 melalui Ethereum, dApp apa pun mencapai skala tak terbatas untuk komputasinya – tanpa mengorbankan komposisi dan keamanan Ethereum, berkat ketergantungan StarkNet pada sistem bukti kriptografi yang paling aman dan terukur – STARK. \r\n\r\nKontrak StarkNet dan OS StarkNet dibuat di Cairo – mendukung penerapan dan penskalaan kasus penggunaan apa pun, apa pun logika bisnisnya.","weiss_rating":{"rating":null,"market_performance_rating":null,"technology_adoption_rating":null},"community":{"official_site":"https://starknet.io/","twitch":null,"twitter":"https://twitter.com/Starknet","telegram":null,"white_paper":"https://starknet.io/docs/"},"price_info":{"high_label":"19.094,92","low_label":"18.034,8","price":18663.398,"price_label":"18.663,39","price_in_idr_label":null,"price_in_idr":null,"price_change":{"24h":{"amount_label":"-155,4179","amount":-155.41799999999785,"rate_label":"-0,82","rate":-0.008258649215763513,"graph_data":[18818.816,18768.15,18724.3,18672.363,18549.3,18588.216,18588.216,18267.176,18777.784,18495.158,18622.212,18577.161,18383.772,18203.514,18323.228,18629.6,18551.832,18488.079999999998,18488.079999999998,18935.532,18998.095999999998,18605.34,18612.079999999998,18614.415999999997]}}},"halt_config":{"warning_info_text":null,"popup_info_text":null,"is_graph_enabled":true,"is_buy_enabled":true,"is_sell_enabled":true,"is_withdraw_enabled":true,"is_deposit_enabled":true,"is_listed":true},"volume24h_label":"168,48M","coin_labels":null,"minimum_amount":15934,"minimum_quantity":0.1,"maximum_quantity":200000,"minimum_tick":0.0001,"quote_tick":0.001,"decimal_point":{"price":2}}