{"symbol":"TRU","asset_name":"TrueFi","asset_logo":"https://www.cryptocompare.com/media/37747178/tru.png","quote_currency":"IDR","currency_symbol":"Rp","transaction_type":["MARKET","LIMIT"],"market_cap_label":"2,41T","current_supply":1154906782,"maximum_supply":1240828859,"start_date":1591142400000,"description":"TrueFi adalah protokol untuk membuat pool berbunga dengan APR tinggi untuk penyedia likuiditas. TrueFi mencakup mekanisme utilitas dan penghargaan menggunakan TrustTokens (TRU) dan memberi penghargaan kepada peserta untuk mempertahankan APR yang stabil dan tinggi.\r\n\r\nTRU adalah token asli dari protokol TrueFi dan digunakan untuk: Pemegang TrustToken pada akhirnya memiliki suara untuk menentukan siapa peminjam yang kredibel di pasar prediksi. TRU memberikan kemampuan kepada pemegangnya untuk memberikan peringkat kredit kepada pihak ketiga. Melalui peringkat kredit TRU, sistem kredit tanpa izin dapat dibangun yang beroperasi murni melalui insentif. Pemilik TRU memiliki bagian kepemilikan dalam membangun sistem kredit baru.","weiss_rating":{"rating":null,"market_performance_rating":null,"technology_adoption_rating":null},"community":{"official_site":"https://truefi.io/","twitch":null,"twitter":"https://x.com/TrueFiDAO","telegram":"https://t.me/jointruefi","white_paper":"https://docs.truefi.io/faq"},"price_info":{"high_label":"2.192,0956","low_label":"1.910,8024","price":1940.1759,"price_label":"1.940,1759","price_in_idr_label":null,"price_in_idr":null,"price_change":{"24h":{"amount_label":"-222,1381","amount":-222.13810000000035,"rate_label":"-10,27","rate":-0.10273165691939298,"graph_data":[2162.3140000000003,2117.9634,2098.3630999999996,2082.2120000000004,2098.2342,2103.5376,2101.785,2074.1543,2025.3784,1998.75,1995.3772000000001,2010.6198000000002,2039.877,2040.128,2004.4881,1991.4825,1976.8512,1967.2848,2021.9976,1976.8512,1910.8024,1943.5163,1941.4104,1940.1759]}}},"halt_config":{"warning_info_text":null,"popup_info_text":null,"is_graph_enabled":true,"is_buy_enabled":true,"is_sell_enabled":true,"is_withdraw_enabled":true,"is_deposit_enabled":true,"is_listed":true},"volume24h_label":"415,26M","coin_labels":["NEW_COIN"],"minimum_amount":81315,"minimum_quantity":1,"maximum_quantity":9222449,"minimum_tick":1,"quote_tick":0.0001,"decimal_point":{"price":4}}