{"symbol":"W","asset_name":"Wormhole","asset_logo":"https://www.cryptocompare.com/media/44224534/w.png","quote_currency":"IDR","currency_symbol":"Rp","transaction_type":["MARKET","LIMIT"],"market_cap_label":"99,71T","current_supply":1800000000,"maximum_supply":10000000000,"start_date":1710115200000,"description":"Wormhole adalah platform interoperabilitas terkemuka yang mendukung aplikasi dan jembatan multichain dalam skala besar. Wormhole memberi pengembang akses ke likuiditas dan pengguna di lebih dari 30 jaringan blockchain terkemuka, memungkinkan kasus penggunaan yang mencakup DeFi, NFT, tata kelola, dan banyak lagi.\r\n\r\nJaringan Wormhole yang lebih luas dipercaya dan digunakan oleh tim seperti Circle dan Uniswap, dan hingga saat ini, platform tersebut telah memfasilitasi transfer lebih dari 35 miliar dolar melalui lebih dari 1 miliar pesan lintas rantai.","weiss_rating":{"rating":null,"market_performance_rating":null,"technology_adoption_rating":null},"community":{"official_site":"https://wormhole.com/","twitch":null,"twitter":"https://twitter.com/wormhole","telegram":"https://t.me/wormholecrypto","white_paper":null},"price_info":{"high_label":"10.985,52","low_label":"9.450,3","price":10039.514,"price_label":"10.039,51","price_in_idr_label":null,"price_in_idr":null,"price_change":{"24h":{"amount_label":"-823,915","amount":-823.9150000000009,"rate_label":"-7,58","rate":-0.07584299579810397,"graph_data":[10863.429,10431.36,10305.392,10428.48,10277.231,10414.95,10087.333,9973.5,9842.699999999999,9662.259,9580.514,9581.099999999999,9528.503999999999,9740.744999999999,9740.744999999999,10002.07,9935.983,9788.662,10150.866,10159.56,10154.592,10252.704,9999.626,10023.163]}}},"halt_config":{"warning_info_text":null,"popup_info_text":null,"is_graph_enabled":true,"is_buy_enabled":true,"is_sell_enabled":true,"is_withdraw_enabled":true,"is_deposit_enabled":true,"is_listed":true},"volume24h_label":"514,99M","coin_labels":["NEW_COIN"],"minimum_amount":81755,"minimum_quantity":0.1,"maximum_quantity":92141578,"minimum_tick":0.1,"quote_tick":0.001,"decimal_point":{"price":2}}