{"symbol":"WIF","asset_name":"dogwifhat","asset_logo":"https://www.cryptocompare.com/media/44154324/wif.png","quote_currency":"IDR","currency_symbol":"Rp","transaction_type":["MARKET","LIMIT"],"market_cap_label":"45,02T","current_supply":998906165,"maximum_supply":null,"start_date":1680307200000,"description":"Meme populer Dogwifhat vibes dengan frens onchain.","weiss_rating":{"rating":null,"market_performance_rating":null,"technology_adoption_rating":null},"community":{"official_site":"https://dogwifcoin.org/","twitch":null,"twitter":"https://twitter.com/dogwifcoin","telegram":"https://t.me/dogwifcoin","white_paper":null},"price_info":{"high_label":"50.316,44","low_label":"44.450,53","price":45584.451,"price_label":"45.584,45","price_in_idr_label":null,"price_in_idr":null,"price_change":{"24h":{"amount_label":"-3.908,209","amount":-3908.2090000000026,"rate_label":"-7,89","rate":-0.07896542638847866,"graph_data":[49492.66,49519.245,49402.2529,49422.2848,48534.393000000004,48937.4746,47704.3872,47712.2085,46949.159999999996,46845.193999999996,46424.0007,46586.1394,46867.2512,46481.911,46421.831000000006,46337.184,45986.551199999994,45259.6001,45010.425599999995,45275.309799999995,45451.3516,45531.6336,45137.604,45597.3108]}}},"halt_config":{"warning_info_text":null,"popup_info_text":null,"is_graph_enabled":true,"is_buy_enabled":true,"is_sell_enabled":true,"is_withdraw_enabled":true,"is_deposit_enabled":true,"is_listed":true},"volume24h_label":"2,89T","coin_labels":["NEW_COIN"],"minimum_amount":81660,"minimum_quantity":0.01,"maximum_quantity":92141578,"minimum_tick":0.01,"quote_tick":0.0001,"decimal_point":{"price":2}}