{"symbol":"XAI","asset_name":"Xai","asset_logo":"https://www.cryptocompare.com/media/44213469/xai.png","quote_currency":"IDR","currency_symbol":"Rp","transaction_type":["MARKET","LIMIT"],"market_cap_label":"16,69T","current_supply":0,"maximum_supply":null,"start_date":1701734400000,"description":"Xai adalah solusi Layer 3 pertama di dunia untuk game AAA. Didukung oleh Teknologi Arbitrum Offchain Labs dengan game dari Ex Populus dan pengembang game lainnya.","weiss_rating":{"rating":null,"market_performance_rating":null,"technology_adoption_rating":null},"community":{"official_site":"https://xai.games/","twitch":null,"twitter":"https://twitter.com/xai_games","telegram":"https://t.me/XaiSentryNodes","white_paper":"https://xai-foundation.gitbook.io/xai-network/xai-blockchain/welcome-to-xai"},"price_info":{"high_label":"16.884,82","low_label":"15.784,96","price":16570.5318,"price_label":"16.570,53","price_in_idr_label":null,"price_in_idr":null,"price_change":{"24h":{"amount_label":"-51,9616","amount":-51.96160000000236,"rate_label":"-0,31","rate":-0.003125981087771246,"graph_data":[16622.493400000003,16593.481,16588.5356,16531.0488,16641.321,16453.9648,16540.552499999998,16307.054399999999,16269.923200000001,16495.9392,16475.9725,16801.0608,16702.33,16535.985,16731.4,16634.5,16626.568,16679.8008,16624.816,16620.9941,16504.7069,16540.2391,16592.9496,16562.442300000002]}}},"halt_config":{"warning_info_text":null,"popup_info_text":null,"is_graph_enabled":true,"is_buy_enabled":true,"is_sell_enabled":true,"is_withdraw_enabled":true,"is_deposit_enabled":true,"is_listed":true},"volume24h_label":"25,25M","coin_labels":null,"minimum_amount":80895,"minimum_quantity":0.1,"maximum_quantity":92141578,"minimum_tick":0.1,"quote_tick":0.0001,"decimal_point":{"price":2}}