{"symbol":"YGG","asset_name":"Yield Guild Games","asset_logo":"https://www.cryptocompare.com/media/37748361/ygg.png","quote_currency":"IDR","currency_symbol":"Rp","transaction_type":["MARKET","LIMIT"],"market_cap_label":"7,9T","current_supply":372387737,"maximum_supply":null,"start_date":1627257600000,"description":"Yield Guild Games (YGGs) adalah organisasi otonom terdesentralisasi (DAO) yang berinvestasi di dunia virtual non-fungible token (NFT). Tujuan organisasi ini adalah untuk mengembangkan ekonomi virtual terbesar di dunia, mengoptimalkan asetnya untuk memaksimalkan utilitas dan berbagi pendapatan dengan para stakeholder.\n\nDalam game terdesentralisasi, Yield Guild Games telah membangun komunitas pemain dan investor yang menghasilkan uang dengan berinvestasi di NFT, yang digunakan di dunia virtual dan game berbasis blockchain. Orang-orang menjadi lebih bersemangat untuk berpartisipasi dalam game play-to-earning, ditambah lagi karena tejadi pandemi, hal tersebut membantu platform ini menjadi semakin populer.\n\nPerusahaan di balik Yield Guild Game adalah studio game yang berbasis di Manila yang didirikan oleh Gabby Dizon, bagian dari tim yang meluncurkan Komunitas Axie Infinity dan Yearn Finance. Beryl Li dan Owl of Moistness mendirikan studio Game. Beryl Li adalah seorang pengusaha, alumnus Universitas Cambridge yang juga menjabat sebagai presiden Cryptocurrency Society pada tahun 2016. Dia juga salah satu pendiri di CapchainX dan merupakan konsultan keuangan berlisensi. Owl of Moistness adalah pengembang blockchain; dia telah membangun algoritme untuk banyak bot dan NFT, termasuk Axie Infinity.","weiss_rating":{"rating":"","market_performance_rating":"","technology_adoption_rating":""},"community":{"official_site":"https://yieldguild.io/","twitch":"","twitter":"https://twitter.com/YieldGuild","telegram":"https://t.me/yieldguildgames","white_paper":"https://yieldguild.io/YGG-Whitepaper-English.pdf"},"price_info":{"high_label":"7.950,162","low_label":"7.222,161","price":7949.673,"price_label":"7.949,673","price_in_idr_label":null,"price_in_idr":null,"price_change":{"24h":{"amount_label":"652,9229","amount":652.9229999999998,"rate_label":"8,94","rate":0.08948134443416586,"graph_data":[7296.75,7335.666,7300.1719,7262.8682,7247.8242,7274.221500000001,7602.9983999999995,7703.549999999999,7695.164400000001,7766.88,7754.3488,7814.118,7900.912499999999,7774.7956,7815.63,7831.901999999999,7848.8820000000005,7827.809,7776.0515,7727.073200000001,7794.423500000001,7898.805200000001,7913.5857,7949.673]}}},"halt_config":{"warning_info_text":null,"popup_info_text":null,"is_graph_enabled":true,"is_buy_enabled":true,"is_sell_enabled":true,"is_withdraw_enabled":true,"is_deposit_enabled":true,"is_listed":true},"volume24h_label":"377,35M","coin_labels":null,"minimum_amount":16256,"minimum_quantity":0.1,"maximum_quantity":295346,"minimum_tick":0.1,"quote_tick":0.0001,"decimal_point":{"price":4}}