{"symbol":"ZIL","asset_name":"Zilliqa","asset_logo":"https://www.cryptocompare.com/media/37746856/zil.png","quote_currency":"IDR","currency_symbol":"Rp","transaction_type":["MARKET","LIMIT"],"market_cap_label":"7,24T","current_supply":18462298202,"maximum_supply":21000000000,"start_date":1548892800000,"description":"Apa itu Zilliqa (ZIL)?\r\nZilliqa adalah blockchain publik dan permissionless yang dirancang untuk menawarkan throughput tinggi dengan kemampuan untuk menyelesaikan ribuan transaksi per detik. Ini berupaya untuk menyelesaikan masalah skalabilitas dan kecepatan blockchain dengan menggunakan sharding sebagai solusi scaling lapis kedua. Platform ini merupakan rumah bagi banyak aplikasi terdesentralisasi, dan per Oktober 2020, ini juga memungkinkan untuk staking dan yield farming.\r\n\r\nPengembangan Zilliqa secara resmi dimulai pada Juni 2017, dan testnet-nya diluncurkan pada Maret 2018. Lebih dari setahun kemudian, pada Juni 2019, platform ini meluncurkan mainnet-nya.\r\n\r\nToken utilitas asli Zilliqa, ZIL, digunakan untuk memproses transaksi di jaringan dan menjalankan kontrak pintar.","weiss_rating":{"rating":"C-","market_performance_rating":"E+","technology_adoption_rating":"C-"},"community":{"official_site":null,"twitch":null,"twitter":null,"telegram":null,"white_paper":null},"price_info":{"high_label":"384,5463","low_label":"371,787","price":376.12800000000004,"price_label":"376,128","price_in_idr_label":null,"price_in_idr":null,"price_change":{"24h":{"amount_label":"-7,146079","amount":-7.146079999999984,"rate_label":"-1,86","rate":-0.018644829830391826,"graph_data":[383.27408,381.59696,379.25436,383.32120000000003,380.90411,383.07734000000005,382.83504,384.3831,380.81415,378.78786,377.69599999999997,377.6238,376.24863,376.58241,374.737,377.019,375.03999,375.18172999999996,373.51517,374.94975999999997,373.78665,373.08411,376.57161,376.12800000000004]}}},"halt_config":{"warning_info_text":null,"popup_info_text":null,"is_graph_enabled":true,"is_buy_enabled":true,"is_sell_enabled":true,"is_withdraw_enabled":true,"is_deposit_enabled":true,"is_listed":true},"volume24h_label":"110,76M","coin_labels":null,"minimum_amount":81625,"minimum_quantity":0.1,"maximum_quantity":9000000,"minimum_tick":0.1,"quote_tick":0.00001,"decimal_point":{"price":4}}